ym2/__init__.py
ym2/__main__.py
ym2/importer.py
ym2/launcher.py
ym2/parser.py
ym2/sweeper.py
ym2-0.1.5.dist-info/METADATA
ym2-0.1.5.dist-info/WHEEL
ym2-0.1.5.dist-info/entry_points.txt
ym2-0.1.5.dist-info/top_level.txt
ym2-0.1.5.dist-info/RECORD
