Metadata-Version: 2.1
Name: ym2
Version: 0.1.5
Requires-Dist: pyyaml
Requires-Dist: omegaconf
